Workbook

Sheet README
B2: Akron Pulse - Infrastructure Cost Model
B3: Operating-cost projection across realistic Akron-only demand scenarios. Prepared for grant budgeting.
B6: HOW TO USE THIS MODEL
B7: Blue cells are inputs you can change. Black cells are formulas. Green cells pull from another sheet.
B8: Edit the Assumptions tab (pricing, per-visit resource use) or the Scenarios tab (visitor / embed volumes)
B9: and every cost figure recalculates automatically.
B11: TABS
B12: Assumptions - vendor pricing & plan limits (2026), and measured per-visit resource consumption.
B13: Scenarios - the model: five demand scenarios from launch to a beyond-Akron stress test.
B14: Grant Ask - recommended budget figures to put in an application.
B16: KEY FINDING
B17: The architecture (CDN-cached app shell, edge-cached first page, lean list payloads, maps gated behind a
... B31: Summit County (538K), and observed engaged-audience proxies (Signal Akron's events guide ~30K subscribers).

Sheet Assumptions
B2: Assumptions
C4: Value | D4: Unit | E4: Source / basis
B5: VENDOR PRICING & PLAN LIMITS (2026)
B6: Vercel Pro - base | C6: 20 | D6: $/mo | E6: Vercel pricing 2026 ($20/seat + $20 usage credit). vercel.com/pricing
B7: Vercel Pro - included bandwidth | C7: 1000 | D7: GB/mo | E7: Pro includes 1 TB bandwidth. vercel.com/pricing
B8: Vercel - bandwidth overage | C8: 0.15 | D8: $/GB | E8: $0.15/GB beyond 1 TB. vercel.com/pricing
B9: Supabase Pro - base | C9: 25 | D9: $/mo | E9: Supabase Pro $25/mo. supabase.com/pricing
B10: Supabase Pro - included egress | C10: 250 | D10: GB/mo | E10: Pro includes 250 GB egress. supabase.com/pricing
B11: Supabase - egress overage | C11: 0.09 | D11: $/GB | E11: $0.09/GB beyond 250 GB. supabase.com/pricing
B12: Mapbox - free web map loads | C12: 50000 | D12: loads/mo | E12: 50,000 free map loads/mo. mapbox.com/pricing
B13: Mapbox - overage (50K-200K) | C13: 5 | D13: $/1k | E13: $5 per 1,000 loads; drops to $3/1k above 200K. mapbox.com/pricing
B14: Transactional email (Resend) - base | C14: 0 | D14: $/mo | E14: Free 3k emails/mo; digest not yet wired. resend.com/pricing
B15: Domain (amortized) | C15: 1.67 | D15: $/mo | E15: ~$20/yr .com registration / renewal.
B16: Scraper compute (small VPS / scheduler) | C16: 12 | D16: $/mo | E16: ~65 Puppeteer scrapers x2/day; small always-on box.
B17: Error monitoring | C17: 0 | D17: $/mo | E17: Sentry / Vercel free tier sufficient at this scale.
B19: PER-VISIT RESOURCE CONSUMPTION (estimated from codebase)
B20: Vercel bandwidth - per main-site session | C20: 0.8 | D20: MB | E20: App shell CDN-cached; blended new+returning + a few optimized images.
B21: Supabase egress - per main-site session | C21: 0.07 | D21: MB | E21: First page edge-cached on Vercel; ~2-4 direct queries, gzipped ~20KB each.
B22: Mapbox loads - per main-site session | C22: 0.15 | D22: loads | E22: Map OFF by default (HomePage view='list'); ~15% of sessions toggle map.
B23: Vercel bandwidth - per embed impression | C23: 0.6 | D23: MB | E23: Same CDN-cached shell; iframe, fewer images in view.
B24: Supabase egress - per embed impression | C24: 0.04 | D24: MB | E24: Usually one locked-filter list query per impression.
B25: Mapbox loads - per embed impression | C25: 0.02 | D25: loads | E25: Embeds default to list; map rarely enabled by partners.
B27: PLANNING PARAMETERS
B28: Contingency / overage buffer | C28: 0.25 | D28: % | E28: Buffer for spikes, image-optimization, Supabase compute add-on, price changes.
B29: Maintenance labor (optional line) | C29: 8 | D29: hrs/mo | E29: Funders often want donated time valued; not a cash cost today.
B30: Maintenance value rate | C30: 50 | D30: $/hr | E30: Conservative blended contractor rate.

Sheet Scenarios
B2: Demand Scenarios & Monthly / Annual Cost
B3: Columns C-F are realistic Akron-only scenarios. Column G is a beyond-Akron stress test to locate the cost cliffs.
B5: SCENARIO | C5: Launch (Yr 1) | D5: Growth | E5: Mature | F5: Peak (Akron ceiling) | G5: Stress (beyond Akron)
B6: Main-site monthly visitors | C6: 5000 | D6: 25000 | E6: 75000 | F6: 200000 | G6: 1000000
B7: Embed impressions / month | C7: 10000 | D7: 75000 | E7: 250000 | F7: 1000000 | G7: 5000000
B8: Embed partner sites | C8: 3 | D8: 10 | E8: 20 | F8: 40 | G8: 100
B10: RESOURCE TOTALS / MONTH
B11: Vercel bandwidth (GB) | C11: =(C6*Assumptions!$C$20+C7*Assumptions!$C$23)/1024 -> 9.765625 | D11: =(D6*Assumptions!$C$20+D7*Assumptions!$C$23)/1024 -> 63.476562 | E11: =(E6*Assumptions!$C$20+E7*Assumptions!$C$23)/1024 -> 205.07812 | F11: =(F6*Assumptions!$C$20+F7*Assumptions!$C$23)/1024 -> 742.1875 | G11: =(G6*Assumptions!$C$20+G7*Assumptions!$C$23)/1024 -> 3710.9375
B12: Supabase egress (GB) | C12: =(C6*Assumptions!$C$21+C7*Assumptions!$C$24)/1024 -> 0.73242188 | D12: =(D6*Assumptions!$C$21+D7*Assumptions!$C$24)/1024 -> 4.6386719 | E12: =(E6*Assumptions!$C$21+E7*Assumptions!$C$24)/1024 -> 14.892578 | F12: =(F6*Assumptions!$C$21+F7*Assumptions!$C$24)/1024 -> 52.734375 | G12: =(G6*Assumptions!$C$21+G7*Assumptions!$C$24)/1024 -> 263.67188
B13: Mapbox map loads | C13: =C6*Assumptions!$C$22+C7*Assumptions!$C$25 -> 950 | D13: =D6*Assumptions!$C$22+D7*Assumptions!$C$25 -> 5250 | E13: =E6*Assumptions!$C$22+E7*Assumptions!$C$25 -> 16250 | F13: =F6*Assumptions!$C$22+F7*Assumptions!$C$25 -> 50000 | G13: =G6*Assumptions!$C$22+G7*Assumptions!$C$25 -> 250000
B14: Vercel bandwidth - % of 1 TB included | C14: =C11/Assumptions!$C$7 -> 0.009765625 | D14: =D11/Assumptions!$C$7 -> 0.063476562 | E14: =E11/Assumptions!$C$7 -> 0.20507812 | F14: =F11/Assumptions!$C$7 -> 0.7421875 | G14: =G11/Assumptions!$C$7 -> 3.7109375
B15: Supabase egress - % of 250 GB included | C15: =C12/Assumptions!$C$10 -> 0.0029296875 | D15: =D12/Assumptions!$C$10 -> 0.018554688 | E15: =E12/Assumptions!$C$10 -> 0.059570312 | F15: =F12/Assumptions!$C$10 -> 0.2109375 | G15: =G12/Assumptions!$C$10 -> 1.0546875
B16: Mapbox loads - % of 50K free | C16: =C13/Assumptions!$C$12 -> 0.019 | D16: =D13/Assumptions!$C$12 -> 0.105 | E16: =E13/Assumptions!$C$12 -> 0.325 | F16: =F13/Assumptions!$C$12 -> 1 | G16: =G13/Assumptions!$C$12 -> 5
B18: MONTHLY COST BY SERVICE
B19: Vercel (hosting + bandwidth + functions) | C19: =Assumptions!$C$6+MAX(0,C11-Assumptions!$C$7)*Assumptions!$C$8 -> 20 | D19: =Assumptions!$C$6+MAX(0,D11-Assumptions!$C$7)*Assumptions!$C$8 -> 20 | E19: =Assumptions!$C$6+MAX(0,E11-Assumptions!$C$7)*Assumptions!$C$8 -> 20 | F19: =Assumptions!$C$6+MAX(0,F11-Assumptions!$C$7)*Assumptions!$C$8 -> 20 | G19: =Assumptions!$C$6+MAX(0,G11-Assumptions!$C$7)*Assumptions!$C$8 -> 426.64062
B20: Supabase (Postgres + egress) | C20: =Assumptions!$C$9+MAX(0,C12-Assumptions!$C$10)*Assumptions!$C$11 -> 25 | D20: =Assumptions!$C$9+MAX(0,D12-Assumptions!$C$10)*Assumptions!$C$11 -> 25 | E20: =Assumptions!$C$9+MAX(0,E12-Assumptions!$C$10)*Assumptions!$C$11 -> 25 | F20: =Assumptions!$C$9+MAX(0,F12-Assumptions!$C$10)*Assumptions!$C$11 -> 25 | G20: =Assumptions!$C$9+MAX(0,G12-Assumptions!$C$10)*Assumptions!$C$11 -> 26.230469
B21: Mapbox (maps) | C21: =MAX(0,C13-Assumptions!$C$12)/1000*Assumptions!$C$13 -> 0 | D21: =MAX(0,D13-Assumptions!$C$12)/1000*Assumptions!$C$13 -> 0 | E21: =MAX(0,E13-Assumptions!$C$12)/1000*Assumptions!$C$13 -> 0 | F21: =MAX(0,F13-Assumptions!$C$12)/1000*Assumptions!$C$13 -> 0 | G21: =MAX(0,G13-Assumptions!$C$12)/1000*Assumptions!$C$13 -> 1000
B22: Transactional email | C22: =Assumptions!$C$14 -> 0 | D22: =Assumptions!$C$14 -> 0 | E22: =Assumptions!$C$14 -> 0 | F22: =Assumptions!$C$14 -> 0 | G22: =Assumptions!$C$14 -> 0
B23: Domain | C23: =Assumptions!$C$15 -> 1.67 | D23: =Assumptions!$C$15 -> 1.67 | E23: =Assumptions!$C$15 -> 1.67 | F23: =Assumptions!$C$15 -> 1.67 | G23: =Assumptions!$C$15 -> 1.67
B24: Scraper compute | C24: =Assumptions!$C$16 -> 12 | D24: =Assumptions!$C$16 -> 12 | E24: =Assumptions!$C$16 -> 12 | F24: =Assumptions!$C$16 -> 12 | G24: =Assumptions!$C$16 -> 12
B25: Error monitoring | C25: =Assumptions!$C$17 -> 0 | D25: =Assumptions!$C$17 -> 0 | E25: =Assumptions!$C$17 -> 0 | F25: =Assumptions!$C$17 -> 0 | G25: =Assumptions!$C$17 -> 0
B27: Infrastructure subtotal / month | C27: =SUM(C19:C25) -> 58.67 | D27: =SUM(D19:D25) -> 58.67 | E27: =SUM(E19:E25) -> 58.67 | F27: =SUM(F19:F25) -> 58.67 | G27: =SUM(G19:G25) -> 1466.5411
B28: Contingency buffer | C28: =C27*Assumptions!$C$28 -> 14.6675 | D28: =D27*Assumptions!$C$28 -> 14.6675 | E28: =E27*Assumptions!$C$28 -> 14.6675 | F28: =F27*Assumptions!$C$28 -> 14.6675 | G28: =G27*Assumptions!$C$28 -> 366.63527
B29: TOTAL MONTHLY (infra + buffer) | C29: =C27+C28 -> 73.3375 | D29: =D27+D28 -> 73.3375 | E29: =E27+E28 -> 73.3375 | F29: =F27+F28 -> 73.3375 | G29: =G27+G28 -> 1833.1764
B30: TOTAL ANNUAL (infra + buffer) | C30: =C29*12 -> 880.05 | D30: =D29*12 -> 880.05 | E30: =E29*12 -> 880.05 | F30: =F29*12 -> 880.05 | G30: =G29*12 -> 21998.116
B32: OPTIONAL: INCLUDING VALUED MAINTENANCE LABOR
B33: Maintenance labor (valued) | C33: =Assumptions!$C$29*Assumptions!$C$30 -> 400 | D33: =Assumptions!$C$29*Assumptions!$C$30 -> 400 | E33: =Assumptions!$C$29*Assumptions!$C$30 -> 400 | F33: =Assumptions!$C$29*Assumptions!$C$30 -> 400 | G33: =Assumptions!$C$29*Assumptions!$C$30 -> 400
B34: TOTAL MONTHLY (infra + buffer + labor) | C34: =C29+C33 -> 473.3375 | D34: =D29+D33 -> 473.3375 | E34: =E29+E33 -> 473.3375 | F34: =F29+F33 -> 473.3375 | G34: =G29+G33 -> 2233.1764
B35: TOTAL ANNUAL (infra + buffer + labor) | C35: =C34*12 -> 5680.05 | D35: =D34*12 -> 5680.05 | E35: =E34*12 -> 5680.05 | F35: =F34*12 -> 5680.05 | G35: =G34*12 -> 26798.116
B37: Akron context: city 189K, Summit County 538K, Akron MSA 702K. 'Peak' assumes deep penetration of an engaged
B38: audience (Signal Akron's events guide reports ~30K newsletter subscribers). 'Stress' (1M visits/5M embeds) is far
B39: beyond what Akron-only demand can produce, shown only to reveal where the first paid overage appears.

Sheet Grant Ask
B2: Recommended Grant Budget
B3: Plan to the 'Mature' scenario so the platform is funded through strong adoption without a mid-grant gap.
B5: ITEM | C5: Amount | D5: Basis
B6: Annual infrastructure - Mature scenario (infra + buffer) | C6: =Scenarios!E30 -> 880.05 | D6: Scenarios tab, Mature, annual infra incl. 25% buffer
B7: Annual infrastructure - Peak / Akron ceiling | C7: =Scenarios!F30 -> 880.05 | D7: Upper bound if the site saturates Akron demand
B8: 3-year infrastructure (Mature) | C8: =Scenarios!E30*3 -> 2640.15 | D8: Typical multi-year grant horizon
B10: Optional: valued maintenance labor / year | C10: =Scenarios!E33*12 -> 4800 | D10: 8 hrs/mo @ $50 - donated today, shown for full-cost accounting
B11: Annual all-in (infra + buffer + labor), Mature | C11: =Scenarios!E35 -> 5680.05 | D11: If the funder wants fully-loaded cost
B12: 3-year all-in (infra + buffer + labor), Mature | C12: =Scenarios!E35*3 -> 17040.15 | D12: Fully-loaded, multi-year
B14: HEADLINE FOR THE APPLICATION
B15: ="Recommended annual operating budget: "&TEXT(Scenarios!E30,"$#,##0")&" (infrastructure incl. contingency, Mature scenario)." -> Recommended annual operating budget: $880 (infrastructure incl. contingency, Mature scenario).
B16: ="Even at the optimistic Akron ceiling the figure is "&TEXT(Scenarios!F30,"$#,##0")&"/yr; the platform is effectively flat-cost." -> Even at the optimistic Akron ceiling the figure is $880/yr; the platform is effectively flat-cost.
